scmlab367104703/__init__.py
scmlab367104703/lab3mod167104703.py
scmlab367104703-0.1.0.dist-info/METADATA
scmlab367104703-0.1.0.dist-info/WHEEL
scmlab367104703-0.1.0.dist-info/top_level.txt
scmlab367104703-0.1.0.dist-info/RECORD
