Metadata-Version: 2.4
Name: scmlab367104703
Version: 0.1.0
Summary: Basic number theory tools: GCD calculation, solving linear Diophantine equations, and listing primes..
Home-page: https://github.com/Amarit1008/ammaritproj
Author: N. Amarittabut
Author-email: nabeel65010@email.com
Requires-Python: >=3.8
Dynamic: author
Dynamic: author-email
Dynamic: description
Dynamic: description-content-type
Dynamic: home-page
Dynamic: requires-python
Dynamic: summary
